mlx_graphs/__init__.py
mlx_graphs/algorithms/__init__.py
mlx_graphs/algorithms/node2vec.py
mlx_graphs/data/__init__.py
mlx_graphs/data/batch.py
mlx_graphs/data/collate.py
mlx_graphs/data/data.py
mlx_graphs/data/utils.py
mlx_graphs/datasets/__init__.py
mlx_graphs/datasets/base_dataset.py
mlx_graphs/datasets/dataset.py
mlx_graphs/datasets/dblp.py
mlx_graphs/datasets/elliptic.py
mlx_graphs/datasets/hetero_dataset.py
mlx_graphs/datasets/imdb.py
mlx_graphs/datasets/karate_club.py
mlx_graphs/datasets/movie_lens_100k.py
mlx_graphs/datasets/ogb_dataset.py
mlx_graphs/datasets/planetoid.py
mlx_graphs/datasets/qm7b.py
mlx_graphs/datasets/superpixel.py
mlx_graphs/datasets/tu_dataset.py
mlx_graphs/datasets/utils/__init__.py
mlx_graphs/datasets/utils/download.py
mlx_graphs/datasets/utils/io.py
mlx_graphs/loaders/__init__.py
mlx_graphs/loaders/dataloaders.py
mlx_graphs/nn/__init__.py
mlx_graphs/nn/graph_network_block.py
mlx_graphs/nn/linear.py
mlx_graphs/nn/message_passing.py
mlx_graphs/nn/conv/__init__.py
mlx_graphs/nn/conv/gat_conv.py
mlx_graphs/nn/conv/gatv2_conv.py
mlx_graphs/nn/conv/gcn_conv.py
mlx_graphs/nn/conv/gin_conv.py
mlx_graphs/nn/conv/rel_conv.py
mlx_graphs/nn/conv/sage_conv.py
mlx_graphs/nn/conv/simple_conv.py
mlx_graphs/nn/norm/__init__.py
mlx_graphs/nn/norm/batch_norm.py
mlx_graphs/nn/norm/instance_norm.py
mlx_graphs/nn/norm/layer_norm.py
mlx_graphs/nn/pooling/__init__.py
mlx_graphs/nn/pooling/global_pooling.py
mlx_graphs/transforms/__init__.py
mlx_graphs/transforms/base_transform.py
mlx_graphs/transforms/normalize_features.py
mlx_graphs/utils/__init__.py
mlx_graphs/utils/array_ops.py
mlx_graphs/utils/convert.py
mlx_graphs/utils/fs.py
mlx_graphs/utils/scatter.py
mlx_graphs/utils/sorting.py
mlx_graphs/utils/topology.py
mlx_graphs/utils/transformations.py
mlx_graphs/utils/validators.py
mlx_graphs-0.0.8.dist-info/licenses/LICENSE
mlx_graphs-0.0.8.dist-info/METADATA
mlx_graphs-0.0.8.dist-info/WHEEL
mlx_graphs-0.0.8.dist-info/top_level.txt
mlx_graphs-0.0.8.dist-info/RECORD
