Metadata-Version: 2.4
Name: mlx-graphs
Version: 0.0.8
Summary: Graph Neural Network library made for Apple Silicon
Author: mlx-graphs contributors
License: MIT License
Project-URL: Homepage, https://mlx-graphs.github.io/mlx-graphs/
Project-URL: Documentation, https://mlx-graphs.github.io/mlx-graphs/
Project-URL: Repository, https://github.com/mlx-graphs/mlx-graphs
Project-URL: Issues, https://github.com/mlx-graphs/mlx-graphs/issues
Classifier: Development Status :: 3 - Alpha
Classifier: License :: OSI Approved :: MIT License
Classifier: Operating System :: MacOS
Classifier: Programming Language :: Python
Requires-Python: >=3.10
License-File: LICENSE
Requires-Dist: mlx>=0.18; sys_platform == "darwin"
Requires-Dist: numpy==1.26.3
Requires-Dist: requests==2.31.0
Requires-Dist: fsspec==2024.2.0
Requires-Dist: tqdm==4.66.1
Provides-Extra: dev
Requires-Dist: pre-commit==3.6.0; extra == "dev"
Provides-Extra: test
Requires-Dist: pytest==7.4.4; extra == "test"
Requires-Dist: scipy==1.12.0; extra == "test"
Requires-Dist: networkx==3.2.1; extra == "test"
Requires-Dist: torch==2.2.0; extra == "test"
Requires-Dist: torch_geometric==2.5.0; extra == "test"
Provides-Extra: docs
Requires-Dist: ipython==8.21.0; extra == "docs"
Requires-Dist: sphinx>=7.2.6; extra == "docs"
Requires-Dist: sphinx-book-theme==1.1.0; extra == "docs"
Requires-Dist: sphinx-autodoc-typehints==1.25.2; extra == "docs"
Requires-Dist: nbsphinx==0.9.3; extra == "docs"
Requires-Dist: sphinx-gallery==0.15.0; extra == "docs"
Provides-Extra: benchmarks
Requires-Dist: scipy==1.12.0; extra == "benchmarks"
Requires-Dist: dgl==2.0.0; extra == "benchmarks"
Requires-Dist: torch==2.2.0; extra == "benchmarks"
Requires-Dist: torch_geometric==2.5.0; extra == "benchmarks"
Requires-Dist: torch_cluster==1.6.3; extra == "benchmarks"
Dynamic: license-file
